{"generatedAt": "2026-04-17T02:17:36+00:00", "symbol": "PA=F", "name": "钯金 Palladium", "lastPrice": 1564.5, "lastDate": "2026-04-13", "netDirection": "看涨", "stopLoss": 1341.3, "primaryPattern": "下降楔形 Falling Wedge", "primaryTarget": null, "bars": [{"date": "2024-04-15", "open": 1029.4, "high": 1037.6, "low": 1025.5, "close": 1025.5}, {"date": "2024-04-22", "open": 1014.7, "high": 1025.9, "low": 957.4, "close": 957.4}, {"date": "2024-04-29", "open": 976.7, "high": 976.7, "low": 938.2, "close": 947.5}, {"date": "2024-05-06", "open": 982.3, "high": 982.3, "low": 955.4, "close": 980.8}, {"date": "2024-05-13", "open": 964.9, "high": 1014.1, "low": 964.9, "close": 1009.9}, {"date": "2024-05-20", "open": 1030.7, "high": 1030.7, "low": 969.1, "close": 969.1}, {"date": "2024-05-27", "open": 976.7, "high": 976.7, "low": 899.2, "close": 899.2}, {"date": "2024-06-03", "open": 913.0, "high": 924.5, "low": 902.0, "close": 909.5}, {"date": "2024-06-10", "open": 896.4, "high": 900.0, "low": 876.5, "close": 890.6}, {"date": "2024-06-17", "open": 876.5, "high": 950.0, "low": 876.5, "close": 918.1}, {"date": "2024-06-24", "open": 981.5, "high": 981.5, "low": 922.7, "close": 977.9}, {"date": "2024-07-01", "open": 979.0, "high": 1040.5, "low": 972.4, "close": 1035.8}, {"date": "2024-07-08", "open": 1011.5, "high": 1011.5, "low": 969.1, "close": 969.1}, {"date": "2024-07-15", "open": 946.7, "high": 953.0, "low": 899.1, "close": 899.1}, {"date": "2024-07-22", "open": 889.2, "high": 922.0, "low": 884.9, "close": 884.9}, {"date": "2024-07-29", "open": 885.8, "high": 922.6, "low": 873.5, "close": 879.2}, {"date": "2024-08-05", "open": 836.0, "high": 905.9, "low": 822.8, "close": 893.5}, {"date": "2024-08-12", "open": 896.5, "high": 941.7, "low": 896.5, "close": 941.7}, {"date": "2024-08-19", "open": 918.7, "high": 942.5, "low": 913.9, "close": 942.5}, {"date": "2024-08-26", "open": 960.2, "high": 989.0, "low": 932.5, "close": 961.1}, {"date": "2024-09-02", "open": 974.0, "high": 974.5, "low": 896.3, "close": 896.3}, {"date": "2024-09-09", "open": 913.0, "high": 1076.0, "low": 899.5, "close": 1076.0}, {"date": "2024-09-16", "open": 1084.4, "high": 1104.7, "low": 1068.3, "close": 1079.9}, {"date": "2024-09-23", "open": 1046.9, "high": 1061.9, "low": 1014.0, "close": 1014.0}, {"date": "2024-09-30", "open": 998.9, "high": 1016.4, "low": 993.6, "close": 995.2}, {"date": "2024-10-07", "open": 1023.0, "high": 1065.4, "low": 1003.6, "close": 1061.8}, {"date": "2024-10-14", "open": 1023.1, "high": 1077.7, "low": 1004.2, "close": 1077.7}, {"date": "2024-10-21", "open": 1048.4, "high": 1199.7, "low": 1048.4, "close": 1199.7}, {"date": "2024-10-28", "open": 1222.0, "high": 1227.0, "low": 1103.8, "close": 1103.8}, {"date": "2024-11-04", "open": 1066.4, "high": 1076.9, "low": 988.9, "close": 988.9}, {"date": "2024-11-11", "open": 979.4, "high": 979.4, "low": 923.4, "close": 941.3}, {"date": "2024-11-18", "open": 1006.2, "high": 1042.6, "low": 1006.2, "close": 1017.0}, {"date": "2024-11-25", "open": 979.8, "high": 1001.5, "low": 970.5, "close": 990.2}, {"date": "2024-12-02", "open": 975.0, "high": 1004.5, "low": 960.3, "close": 960.3}, {"date": "2024-12-09", "open": 980.5, "high": 1002.7, "low": 953.1, "close": 953.1}, {"date": "2024-12-16", "open": 944.8, "high": 944.8, "low": 897.1, "close": 906.6}, {"date": "2024-12-23", "open": 915.3, "high": 938.3, "low": 893.6, "close": 893.6}, {"date": "2024-12-30", "open": 893.5, "high": 915.6, "low": 893.5, "close": 915.6}, {"date": "2025-01-06", "open": 909.6, "high": 961.7, "low": 909.6, "close": 961.7}, {"date": "2025-01-13", "open": 934.8, "high": 965.5, "low": 934.8, "close": 960.5}, {"date": "2025-01-20", "open": 972.5, "high": 1010.2, "low": 972.5, "close": 1001.2}, {"date": "2025-01-27", "open": 963.6, "high": 1066.9, "low": 954.6, "close": 1066.9}, {"date": "2025-02-03", "open": 1039.2, "high": 1039.2, "low": 977.8, "close": 977.8}, {"date": "2025-02-10", "open": 998.7, "high": 1015.3, "low": 982.6, "close": 1005.0}, {"date": "2025-02-17", "open": 1008.7, "high": 1009.0, "low": 987.3, "close": 988.1}, {"date": "2025-02-24", "open": 940.6, "high": 940.6, "low": 890.0, "close": 899.7}, {"date": "2025-03-03", "open": 951.2, "high": 952.0, "low": 939.4, "close": 945.8}, {"date": "2025-03-10", "open": 959.0, "high": 980.0, "low": 938.2, "close": 962.3}, {"date": "2025-03-17", "open": 963.6, "high": 966.2, "low": 939.1, "close": 951.2}, {"date": "2025-03-24", "open": 948.0, "high": 974.3, "low": 947.7, "close": 974.3}, {"date": "2025-03-31", "open": 991.2, "high": 991.3, "low": 896.2, "close": 896.2}, {"date": "2025-04-07", "open": 876.6, "high": 896.8, "low": 876.6, "close": 896.8}, {"date": "2025-04-14", "open": 946.6, "high": 969.8, "low": 946.6, "close": 955.4}, {"date": "2025-04-21", "open": 925.7, "high": 947.9, "low": 925.7, "close": 931.0}, {"date": "2025-04-28", "open": 954.0, "high": 965.5, "low": 930.2, "close": 946.9}, {"date": "2025-05-05", "open": 938.5, "high": 979.4, "low": 938.5, "close": 978.0}, {"date": "2025-05-12", "open": 938.0, "high": 964.2, "low": 938.0, "close": 956.8}, {"date": "2025-05-19", "open": 979.2, "high": 1046.6, "low": 979.2, "close": 1001.5}, {"date": "2025-05-26", "open": 977.3, "high": 977.3, "low": 957.0, "close": 961.3}, {"date": "2025-06-02", "open": 977.0, "high": 1060.6, "low": 977.0, "close": 1060.6}, {"date": "2025-06-09", "open": 1079.5, "high": 1106.0, "low": 1039.6, "close": 1039.6}, {"date": "2025-06-16", "open": 1055.5, "high": 1067.0, "low": 1032.0, "close": 1052.8}, {"date": "2025-06-23", "open": 1088.6, "high": 1145.6, "low": 1065.4, "close": 1145.6}, {"date": "2025-06-30", "open": 1102.1, "high": 1157.0, "low": 1102.1, "close": 1136.5}, {"date": "2025-07-07", "open": 1103.7, "high": 1273.0, "low": 1103.7, "close": 1273.0}, {"date": "2025-07-14", "open": 1230.5, "high": 1360.0, "low": 1230.5, "close": 1291.9}, {"date": "2025-07-21", "open": 1291.4, "high": 1315.6, "low": 1243.4, "close": 1243.4}, {"date": "2025-07-28", "open": 1280.5, "high": 1280.5, "low": 1196.1, "close": 1207.9}, {"date": "2025-08-04", "open": 1194.8, "high": 1194.8, "low": 1133.2, "close": 1133.2}, {"date": "2025-08-11", "open": 1149.4, "high": 1149.4, "low": 1107.6, "close": 1107.6}, {"date": "2025-08-18", "open": 1121.4, "high": 1123.5, "low": 1101.8, "close": 1123.5}, {"date": "2025-08-25", "open": 1087.5, "high": 1115.0, "low": 1082.0, "close": 1105.2}, {"date": "2025-09-01", "open": 1130.0, "high": 1168.5, "low": 1111.6, "close": 1111.6}, {"date": "2025-09-08", "open": 1121.5, "high": 1244.0, "low": 1121.5, "close": 1229.3}, {"date": "2025-09-15", "open": 1204.0, "high": 1204.0, "low": 1150.8, "close": 1150.8}, {"date": "2025-09-22", "open": 1155.0, "high": 1291.4, "low": 1155.0, "close": 1291.4}, {"date": "2025-09-29", "open": 1298.0, "high": 1301.5, "low": 1239.8, "close": 1273.0}, {"date": "2025-10-06", "open": 1287.5, "high": 1493.0, "low": 1280.0, "close": 1447.6}, {"date": "2025-10-13", "open": 1509.4, "high": 1655.0, "low": 1499.2, "close": 1499.2}, {"date": "2025-10-20", "open": 1514.8, "high": 1514.8, "low": 1412.6, "close": 1463.6}, {"date": "2025-10-27", "open": 1415.9, "high": 1473.0, "low": 1402.7, "close": 1444.7}, {"date": "2025-11-03", "open": 1446.9, "high": 1446.9, "low": 1388.1, "close": 1397.3}, {"date": "2025-11-10", "open": 1443.1, "high": 1517.0, "low": 1416.0, "close": 1420.7}, {"date": "2025-11-17", "open": 1413.9, "high": 1419.4, "low": 1382.4, "close": 1383.6}, {"date": "2025-11-24", "open": 1387.5, "high": 1468.6, "low": 1387.5, "close": 1468.6}, {"date": "2025-12-01", "open": 1478.5, "high": 1479.0, "low": 1444.8, "close": 1472.4}, {"date": "2025-12-08", "open": 1495.5, "high": 1555.5, "low": 1458.3, "close": 1514.2}, {"date": "2025-12-15", "open": 1592.8, "high": 1749.0, "low": 1592.8, "close": 1749.0}, {"date": "2025-12-22", "open": 1815.0, "high": 1984.7, "low": 1766.3, "close": 1984.7}, {"date": "2025-12-29", "open": 1648.3, "high": 1706.7, "low": 1629.2, "close": 1668.0}, {"date": "2026-01-05", "open": 1700.0, "high": 1865.6, "low": 1680.0, "close": 1853.0}, {"date": "2026-01-12", "open": 1921.3, "high": 1921.3, "low": 1805.2, "close": 1805.2}, {"date": "2026-01-19", "open": 1890.9, "high": 2033.5, "low": 1865.2, "close": 2010.0}, {"date": "2026-01-26", "open": 2064.5, "high": 2169.8999, "low": 1688.3, "close": 1688.3}, {"date": "2026-02-02", "open": 1643.5, "high": 1746.1, "low": 1549.5, "close": 1732.7}, {"date": "2026-02-09", "open": 1737.1, "high": 1737.1, "low": 1650.3, "close": 1697.5}, {"date": "2026-02-16", "open": 1675.2, "high": 1774.2, "low": 1675.2, "close": 1774.2}, {"date": "2026-02-23", "open": 1772.2, "high": 1842.0, "low": 1727.5, "close": 1792.2}, {"date": "2026-03-02", "open": 1766.5, "high": 1767.5, "low": 1620.2, "close": 1631.7}, {"date": "2026-03-09", "open": 1591.5, "high": 1668.7, "low": 1554.1, "close": 1554.1}, {"date": "2026-03-16", "open": 1584.5, "high": 1614.0, "low": 1387.0, "close": 1424.8}, {"date": "2026-03-23", "open": 1371.0, "high": 1422.0, "low": 1341.3, "close": 1390.9}, {"date": "2026-03-30", "open": 1413.5, "high": 1491.4, "low": 1402.5, "close": 1491.4}, {"date": "2026-04-06", "open": 1476.2, "high": 1586.9, "low": 1442.0, "close": 1528.1}, {"date": "2026-04-13", "open": 1526.5, "high": 1587.0, "low": 1525.0, "close": 1564.5}], "patterns": [{"pattern": "下降楔形 Falling Wedge", "direction": "看涨", "high_slope": -0.66, "low_slope": -0.58, "upper_bound": 1630.71, "lower_bound": 1498.4343, "compression_ratio": 0.84, "status": "楔形成立中", "symbol": "PA=F", "name": "钯金 Palladium", "last_price": 1561.0, "last_date": "2026-04-13"}]}