{
  "generatedAt": "2026-04-17T06:17:02+00:00",
  "key": "futures",
  "count": 5,
  "entries": [
    {
      "date": "2026-04-16",
      "title": "期货日日报 2026-04-16",
      "preview": "2026 年 04 月 16 日 生成于 14:16 交易日 2026-04-16 ✓ 席位数据已采集 ：0 个品种，检出 39 个散户-机构分歧信号。",
      "file": "futures/期货日日报_2026-04-16.html",
      "bytes": 22323
    },
    {
      "date": "2026-04-15",
      "title": "期货日日报 2026-04-15",
      "preview": "2026 年 04 月 15 日 生成于 18:06 交易日 2026-04-15 ✓ 席位数据已采集 ：64 个品种，检出 42 个散户-机构分歧信号。",
      "file": "futures/期货日日报_2026-04-15.html",
      "bytes": 38334
    },
    {
      "date": "2026-04-14",
      "title": "期货日日报 2026-04-14",
      "preview": "2026 年 04 月 14 日 生成于 19:20 交易日 2026-04-14 ✓ 席位数据已采集 ：64 个品种，检出 42 个散户-机构分歧信号。",
      "file": "futures/期货日日报_2026-04-14.html",
      "bytes": 38410
    },
    {
      "date": "2026-04-13",
      "title": "期货日日报 2026-04-13",
      "preview": "2026 年 04 月 13 日 生成于 18:48 交易日 2026-04-13 ✓ 席位数据已采集 ：64 个品种，检出 43 个散户-机构分歧信号。",
      "file": "futures/期货日日报_2026-04-13.html",
      "bytes": 37705
    },
    {
      "date": "2026-04-10",
      "title": "期货日日报 2026-04-10",
      "preview": "2026 年 04 月 10 日 生成于 11:18 交易日 2026-04-10 ✓ 席位数据已采集 ：64 个品种，检出 42 个散户-机构分歧信号。",
      "file": "futures/期货日日报_2026-04-10.html",
      "bytes": 44150
    }
  ]
}