{
  "generatedAt": "2026-04-17T03:01:10+00:00",
  "dataAsOf": "2026-04-13",
  "summary": {
    "symbolsWithSignal": 69,
    "signalsFound": 103,
    "bullish": 28,
    "bearish": 30,
    "neutral": 45
  },
  "candidates": [
    {
      "symbol": "XLV",
      "nameEn": "ETF XLV",
      "nameZh": "医疗",
      "category": "stocks_etf",
      "lastPrice": 146.61,
      "lastDate": "2026-04-13",
      "score": 4,
      "finalScore": 51.43,
      "direction": "bear",
      "primaryPattern": "头肩顶 H&S Top",
      "patterns": [
        {
          "type": "H&S Top",
          "typeZh": "头肩顶",
          "direction": "bear",
          "status": "Neckline breached",
          "statusZh": "已突破颈线",
          "resistance": null,
          "support": null,
          "ageWeeks": 7
        },
        {
          "type": "Rectangle",
          "typeZh": "矩形整理中",
          "direction": "neutral",
          "status": "区间内 (11次触阻力, 7次触支撑)",
          "statusZh": "区间内 (11次触阻力, 7次触支撑)",
          "resistance": 159.4844,
          "support": 141.8231,
          "ageWeeks": null
        }
      ],
      "trade": {
        "entry": 159.4844,
        "stop": 151.2283,
        "target": 146.5077,
        "riskPct": 3.15,
        "rr": 0.02
      }
    },
    {
      "symbol": "ZB=F",
      "nameEn": "T-Bond",
      "nameZh": "30年国债",
      "category": "futures",
      "lastPrice": 113.6562,
      "lastDate": "2026-04-13",
      "score": 4,
      "finalScore": 49.89,
      "direction": "bear",
      "primaryPattern": "头肩顶 H&S Top",
      "patterns": [
        {
          "type": "H&S Top",
          "typeZh": "头肩顶",
          "direction": "bear",
          "status": "Neckline breached",
          "statusZh": "已突破颈线",
          "resistance": null,
          "support": null,
          "ageWeeks": 20
        },
        {
          "type": "Rectangle",
          "typeZh": "矩形整理中",
          "direction": "neutral",
          "status": "区间内 (12次触阻力, 9次触支撑)",
          "statusZh": "区间内 (12次触阻力, 9次触支撑)",
          "resistance": 119.5078,
          "support": 112.4219,
          "ageWeeks": null
        }
      ],
      "trade": {
        "entry": 119.5078,
        "stop": 115.7188,
        "target": 112.7812,
        "riskPct": 1.81,
        "rr": 0.42
      }
    },
    {
      "symbol": "ZN=F",
      "nameEn": "T-Note",
      "nameZh": "10年国债",
      "category": "futures",
      "lastPrice": 111.1875,
      "lastDate": "2026-04-13",
      "score": 4,
      "finalScore": 49.1,
      "direction": "bear",
      "primaryPattern": "头肩顶 H&S Top",
      "patterns": [
        {
          "type": "H&S Top",
          "typeZh": "头肩顶",
          "direction": "bear",
          "status": "Testing neckline",
          "statusZh": "测试颈线中",
          "resistance": null,
          "support": null,
          "ageWeeks": 20
        },
        {
          "type": "Rectangle",
          "typeZh": "矩形整理中",
          "direction": "neutral",
          "status": "区间内 (22次触阻力, 19次触支撑)",
          "statusZh": "区间内 (22次触阻力, 19次触支撑)",
          "resistance": 113.9414,
          "support": 110.2305,
          "ageWeeks": null
        }
      ],
      "trade": {
        "entry": 113.9414,
        "stop": 112.25,
        "target": 110.5312,
        "riskPct": 0.96,
        "rr": 0.62
      }
    },
    {
      "symbol": "BRK-B",
      "nameEn": "Berkshire",
      "nameZh": "伯克希尔",
      "category": "stocks_etf",
      "lastPrice": 475.12,
      "lastDate": "2026-04-13",
      "score": 4,
      "finalScore": 48.62,
      "direction": "bear",
      "primaryPattern": "头肩顶 H&S Top",
      "patterns": [
        {
          "type": "H&S Top",
          "typeZh": "头肩顶",
          "direction": "bear",
          "status": "Testing neckline",
          "statusZh": "测试颈线中",
          "resistance": null,
          "support": null,
          "ageWeeks": 10
        },
        {
          "type": "Rectangle",
          "typeZh": "矩形整理中",
          "direction": "neutral",
          "status": "区间内 (10次触阻力, 8次触支撑)",
          "statusZh": "区间内 (10次触阻力, 8次触支撑)",
          "resistance": 516.035,
          "support": 468.07,
          "ageWeeks": null
        }
      ],
      "trade": {
        "entry": 516.035,
        "stop": 496.96,
        "target": 430.59,
        "riskPct": 4.6,
        "rr": 2.04
      }
    },
    {
      "symbol": "ZW=F",
      "nameEn": "Wheat",
      "nameZh": "小麦",
      "category": "futures",
      "lastPrice": 608.0,
      "lastDate": "2026-04-13",
      "score": 3,
      "finalScore": 48.43,
      "direction": "bull",
      "primaryPattern": "头肩底 Inv H&S",
      "patterns": [
        {
          "type": "Inverse H&S",
          "typeZh": "头肩底",
          "direction": "bull",
          "status": "Neckline breached",
          "statusZh": "已突破颈线",
          "resistance": null,
          "support": null,
          "ageWeeks": 20
        }
      ],
      "trade": {
        "entry": null,
        "stop": 567.5,
        "target": 617.75,
        "riskPct": 6.66,
        "rr": 0.24
      }
    },
    {
      "symbol": "6C=F",
      "nameEn": "CAD",
      "nameZh": "加元",
      "category": "futures",
      "lastPrice": 0.7317,
      "lastDate": "2026-04-13",
      "score": 4,
      "finalScore": 48.09,
      "direction": "bull",
      "primaryPattern": "头肩底 Inv H&S",
      "patterns": [
        {
          "type": "Inverse H&S",
          "typeZh": "头肩底",
          "direction": "bull",
          "status": "Testing neckline",
          "statusZh": "测试颈线中",
          "resistance": null,
          "support": null,
          "ageWeeks": 13
        },
        {
          "type": "Rectangle",
          "typeZh": "矩形整理中",
          "direction": "neutral",
          "status": "区间内 (16次触阻力, 15次触支撑)",
          "statusZh": "区间内 (16次触阻力, 15次触支撑)",
          "resistance": 0.7402,
          "support": 0.7085,
          "ageWeeks": null
        }
      ],
      "trade": {
        "entry": 0.7402,
        "stop": 0.7168,
        "target": 0.7574,
        "riskPct": 2.04,
        "rr": 1.72
      }
    },
    {
      "symbol": "NZDUSD=X",
      "nameEn": "NZD/USD",
      "nameZh": "纽元/美元",
      "category": "forex",
      "lastPrice": 0.5885,
      "lastDate": "2026-04-13",
      "score": 4,
      "finalScore": 47.52,
      "direction": "bull",
      "primaryPattern": "头肩底 Inv H&S",
      "patterns": [
        {
          "type": "Inverse H&S",
          "typeZh": "头肩底",
          "direction": "bull",
          "status": "Testing neckline",
          "statusZh": "测试颈线中",
          "resistance": null,
          "support": null,
          "ageWeeks": 14
        },
        {
          "type": "Rectangle",
          "typeZh": "矩形整理中",
          "direction": "neutral",
          "status": "区间内 (8次触阻力, 7次触支撑)",
          "statusZh": "区间内 (8次触阻力, 7次触支撑)",
          "resistance": 0.6072,
          "support": 0.5597,
          "ageWeeks": null
        }
      ],
      "trade": {
        "entry": 0.6072,
        "stop": 0.5688,
        "target": 0.621,
        "riskPct": 3.35,
        "rr": 1.65
      }
    },
    {
      "symbol": "DBA",
      "nameEn": "ETF DBA",
      "nameZh": "农产品",
      "category": "stocks_etf",
      "lastPrice": 27.11,
      "lastDate": "2026-04-13",
      "score": 4,
      "finalScore": 46.95,
      "direction": "bear",
      "primaryPattern": "头肩顶 H&S Top",
      "patterns": [
        {
          "type": "H&S Top",
          "typeZh": "头肩顶",
          "direction": "bear",
          "status": "Forming",
          "statusZh": "右肩形成中",
          "resistance": null,
          "support": null,
          "ageWeeks": 11
        },
        {
          "type": "Rectangle",
          "typeZh": "矩形整理中",
          "direction": "neutral",
          "status": "区间内 (6次触阻力, 6次触支撑)",
          "statusZh": "区间内 (6次触阻力, 6次触支撑)",
          "resistance": 27.315,
          "support": 24.6848,
          "ageWeeks": null
        }
      ],
      "trade": {
        "entry": 27.315,
        "stop": 27.37,
        "target": 24.93,
        "riskPct": 0.96,
        "rr": 8.38
      }
    },
    {
      "symbol": "EURJPY=X",
      "nameEn": "EUR/JPY",
      "nameZh": "欧元/日元",
      "category": "forex",
      "lastPrice": 187.682,
      "lastDate": "2026-04-13",
      "score": 4,
      "finalScore": 46.72,
      "direction": "bear",
      "primaryPattern": "头肩顶 H&S Top",
      "patterns": [
        {
          "type": "H&S Top",
          "typeZh": "头肩顶",
          "direction": "bear",
          "status": "Forming",
          "statusZh": "右肩形成中",
          "resistance": null,
          "support": null,
          "ageWeeks": 9
        },
        {
          "type": "Rectangle",
          "typeZh": "矩形整理中",
          "direction": "neutral",
          "status": "区间内 (19次触阻力, 5次触支撑)",
          "statusZh": "区间内 (19次触阻力, 5次触支撑)",
          "resistance": 186.8417,
          "support": 175.9467,
          "ageWeeks": null
        }
      ],
      "trade": {
        "entry": 186.8417,
        "stop": 187.737,
        "target": 178.0032,
        "riskPct": 0.03,
        "rr": 175.98
      }
    },
    {
      "symbol": "GBPCAD=X",
      "nameEn": "GBP/CAD",
      "nameZh": "英镑/加元",
      "category": "forex",
      "lastPrice": 1.8516,
      "lastDate": "2026-04-13",
      "score": 4,
      "finalScore": 46.46,
      "direction": "bear",
      "primaryPattern": "头肩顶 H&S Top",
      "patterns": [
        {
          "type": "H&S Top",
          "typeZh": "头肩顶",
          "direction": "bear",
          "status": "Testing neckline",
          "statusZh": "测试颈线中",
          "resistance": null,
          "support": null,
          "ageWeeks": 19
        },
        {
          "type": "Rectangle",
          "typeZh": "矩形整理中",
          "direction": "neutral",
          "status": "区间内 (24次触阻力, 21次触支撑)",
          "statusZh": "区间内 (24次触阻力, 21次触支撑)",
          "resistance": 1.8789,
          "support": 1.8142,
          "ageWeeks": null
        }
      ],
      "trade": {
        "entry": 1.8789,
        "stop": 1.8693,
        "target": 1.8068,
        "riskPct": 0.95,
        "rr": 2.53
      }
    },
    {
      "symbol": "EURCHF=X",
      "nameEn": "EUR/CHF",
      "nameZh": "欧元/瑞郎",
      "category": "forex",
      "lastPrice": 0.9226,
      "lastDate": "2026-04-13",
      "score": 4,
      "finalScore": 46.23,
      "direction": "bear",
      "primaryPattern": "头肩顶 H&S Top",
      "patterns": [
        {
          "type": "H&S Top",
          "typeZh": "头肩顶",
          "direction": "bear",
          "status": "Testing neckline",
          "statusZh": "测试颈线中",
          "resistance": null,
          "support": null,
          "ageWeeks": 13
        },
        {
          "type": "Rectangle",
          "typeZh": "矩形整理中",
          "direction": "neutral",
          "status": "区间内 (21次触阻力, 12次触支撑)",
          "statusZh": "区间内 (21次触阻力, 12次触支撑)",
          "resistance": 0.9374,
          "support": 0.9018,
          "ageWeeks": null
        }
      ],
      "trade": {
        "entry": 0.9374,
        "stop": 0.9266,
        "target": 0.9157,
        "riskPct": 0.43,
        "rr": 1.73
      }
    },
    {
      "symbol": "XLF",
      "nameEn": "ETF XLF",
      "nameZh": "金融",
      "category": "stocks_etf",
      "lastPrice": 52.03,
      "lastDate": "2026-04-13",
      "score": 4,
      "finalScore": 45.51,
      "direction": "bear",
      "primaryPattern": "头肩顶 H&S Top",
      "patterns": [
        {
          "type": "H&S Top",
          "typeZh": "头肩顶",
          "direction": "bear",
          "status": "Testing neckline",
          "statusZh": "测试颈线中",
          "resistance": null,
          "support": null,
          "ageWeeks": 9
        },
        {
          "type": "Rectangle",
          "typeZh": "矩形整理中",
          "direction": "neutral",
          "status": "区间内 (6次触阻力, 4次触支撑)",
          "statusZh": "区间内 (6次触阻力, 4次触支撑)",
          "resistance": 55.4067,
          "support": 48.1355,
          "ageWeeks": null
        }
      ],
      "trade": {
        "entry": 55.4067,
        "stop": 52.41,
        "target": 48.7494,
        "riskPct": 0.73,
        "rr": 8.63
      }
    },
    {
      "symbol": "6E=F",
      "nameEn": "Euro FX",
      "nameZh": "欧元",
      "category": "futures",
      "lastPrice": 1.1809,
      "lastDate": "2026-04-13",
      "score": 4,
      "finalScore": 44.13,
      "direction": "bear",
      "primaryPattern": "头肩顶 H&S Top",
      "patterns": [
        {
          "type": "H&S Top",
          "typeZh": "头肩顶",
          "direction": "bear",
          "status": "Forming",
          "statusZh": "右肩形成中",
          "resistance": null,
          "support": null,
          "ageWeeks": 17
        },
        {
          "type": "Rectangle",
          "typeZh": "矩形整理中",
          "direction": "neutral",
          "status": "区间内 (18次触阻力, 17次触支撑)",
          "statusZh": "区间内 (18次触阻力, 17次触支撑)",
          "resistance": 1.1918,
          "support": 1.1424,
          "ageWeeks": null
        }
      ],
      "trade": {
        "entry": 1.1918,
        "stop": 1.1839,
        "target": 1.1146,
        "riskPct": 0.26,
        "rr": 22.1
      }
    },
    {
      "symbol": "HE=F",
      "nameEn": "Lean Hogs",
      "nameZh": "瘦肉猪",
      "category": "futures",
      "lastPrice": 101.7,
      "lastDate": "2026-04-13",
      "score": 3,
      "finalScore": 43.52,
      "direction": "bull",
      "primaryPattern": "宽体K线 Wide Bodied Bar (WBB)",
      "patterns": [
        {
          "type": "Wide Bodied Bar",
          "typeZh": "宽体K线",
          "direction": "bull",
          "status": "本周WBB (看涨), 范围是均值的5.6倍",
          "statusZh": "本周WBB (看涨), 范围是均值的5.6倍",
          "resistance": null,
          "support": null,
          "ageWeeks": null
        }
      ],
      "trade": {
        "entry": null,
        "stop": 94.48,
        "target": null,
        "riskPct": 7.1,
        "rr": null
      }
    },
    {
      "symbol": "ZF=F",
      "nameEn": "T-Note",
      "nameZh": "5年国债",
      "category": "futures",
      "lastPrice": 108.2891,
      "lastDate": "2026-04-13",
      "score": 3,
      "finalScore": 43.32,
      "direction": "bear",
      "primaryPattern": "头肩顶 H&S Top",
      "patterns": [
        {
          "type": "H&S Top",
          "typeZh": "头肩顶",
          "direction": "bear",
          "status": "Testing neckline",
          "statusZh": "测试颈线中",
          "resistance": null,
          "support": null,
          "ageWeeks": 20
        }
      ],
      "trade": {
        "entry": null,
        "stop": 108.9688,
        "target": 107.7656,
        "riskPct": 0.63,
        "rr": 0.77
      }
    },
    {
      "symbol": "ZT=F",
      "nameEn": "T-Note",
      "nameZh": "2年国债",
      "category": "futures",
      "lastPrice": 103.7656,
      "lastDate": "2026-04-13",
      "score": 3,
      "finalScore": 42.84,
      "direction": "bear",
      "primaryPattern": "头肩顶 H&S Top",
      "patterns": [
        {
          "type": "H&S Top",
          "typeZh": "头肩顶",
          "direction": "bear",
          "status": "Testing neckline",
          "statusZh": "测试颈线中",
          "resistance": null,
          "support": null,
          "ageWeeks": 20
        }
      ],
      "trade": {
        "entry": null,
        "stop": 103.9297,
        "target": 103.543,
        "riskPct": 0.16,
        "rr": 1.36
      }
    },
    {
      "symbol": "EURGBP=X",
      "nameEn": "EUR/GBP",
      "nameZh": "欧元/英镑",
      "category": "forex",
      "lastPrice": 0.8712,
      "lastDate": "2026-04-13",
      "score": 3,
      "finalScore": 42.84,
      "direction": "bear",
      "primaryPattern": "头肩顶 H&S Top",
      "patterns": [
        {
          "type": "H&S Top",
          "typeZh": "头肩顶",
          "direction": "bear",
          "status": "Testing neckline",
          "statusZh": "测试颈线中",
          "resistance": null,
          "support": null,
          "ageWeeks": 12
        }
      ],
      "trade": {
        "entry": null,
        "stop": 0.8742,
        "target": 0.8448,
        "riskPct": 0.35,
        "rr": 8.8
      }
    },
    {
      "symbol": "XLK",
      "nameEn": "ETF XLK",
      "nameZh": "科技",
      "category": "stocks_etf",
      "lastPrice": 152.02,
      "lastDate": "2026-04-13",
      "score": 3,
      "finalScore": 42.25,
      "direction": "bull",
      "primaryPattern": "头肩底 Inv H&S",
      "patterns": [
        {
          "type": "Inverse H&S",
          "typeZh": "头肩底",
          "direction": "bull",
          "status": "Testing neckline",
          "statusZh": "测试颈线中",
          "resistance": null,
          "support": null,
          "ageWeeks": 17
        }
      ],
      "trade": {
        "entry": null,
        "stop": 137.1873,
        "target": 171.7755,
        "riskPct": 9.76,
        "rr": 1.33
      }
    },
    {
      "symbol": "IWM",
      "nameEn": "2000ETF IWM",
      "nameZh": "罗素",
      "category": "stocks_etf",
      "lastPrice": 269.95,
      "lastDate": "2026-04-13",
      "score": 4,
      "finalScore": 40.3,
      "direction": "bear",
      "primaryPattern": "头肩顶 H&S Top",
      "patterns": [
        {
          "type": "H&S Top",
          "typeZh": "头肩顶",
          "direction": "bear",
          "status": "Forming",
          "statusZh": "右肩形成中",
          "resistance": null,
          "support": null,
          "ageWeeks": 9
        },
        {
          "type": "Rectangle",
          "typeZh": "矩形整理中",
          "direction": "neutral",
          "status": "区间内 (8次触阻力, 3次触支撑)",
          "statusZh": "区间内 (8次触阻力, 3次触支撑)",
          "resistance": 269.8831,
          "support": 232.6272,
          "ageWeeks": null
        }
      ],
      "trade": {
        "entry": 269.8831,
        "stop": 270.35,
        "target": 238.0765,
        "riskPct": 0.15,
        "rr": 79.68
      }
    },
    {
      "symbol": "USDMXN=X",
      "nameEn": "USD/MXN",
      "nameZh": "美元/墨西哥比索",
      "category": "forex",
      "lastPrice": 17.242,
      "lastDate": "2026-04-13",
      "score": 4,
      "finalScore": 40.19,
      "direction": "bull",
      "primaryPattern": "头肩底 Inv H&S",
      "patterns": [
        {
          "type": "Inverse H&S",
          "typeZh": "头肩底",
          "direction": "bull",
          "status": "Forming",
          "statusZh": "右肩形成中",
          "resistance": null,
          "support": null,
          "ageWeeks": 22
        },
        {
          "type": "Rectangle",
          "typeZh": "矩形整理中",
          "direction": "neutral",
          "status": "区间内 (10次触阻力, 9次触支撑)",
          "statusZh": "区间内 (10次触阻力, 9次触支撑)",
          "resistance": 18.5843,
          "support": 17.1,
          "ageWeeks": null
        }
      ],
      "trade": {
        "entry": 18.5843,
        "stop": 17.1971,
        "target": 19.5184,
        "riskPct": 0.26,
        "rr": 50.7
      }
    },
    {
      "symbol": "RTY=F",
      "nameEn": "2000 Russell",
      "nameZh": "罗素",
      "category": "futures",
      "lastPrice": 2735.8,
      "lastDate": "2026-04-13",
      "score": 4,
      "finalScore": 39.4,
      "direction": "bear",
      "primaryPattern": "头肩顶 H&S Top",
      "patterns": [
        {
          "type": "H&S Top",
          "typeZh": "头肩顶",
          "direction": "bear",
          "status": "Forming",
          "statusZh": "右肩形成中",
          "resistance": null,
          "support": null,
          "ageWeeks": 9
        },
        {
          "type": "Rectangle",
          "typeZh": "矩形整理中",
          "direction": "neutral",
          "status": "区间内 (8次触阻力, 3次触支撑)",
          "statusZh": "区间内 (8次触阻力, 3次触支撑)",
          "resistance": 2733.65,
          "support": 2357.925,
          "ageWeeks": null
        }
      ],
      "trade": {
        "entry": 2733.65,
        "stop": 2738.2,
        "target": 2384.4001,
        "riskPct": 0.09,
        "rr": 146.42
      }
    },
    {
      "symbol": "6A=F",
      "nameEn": "AUD",
      "nameZh": "澳元",
      "category": "futures",
      "lastPrice": 0.7157,
      "lastDate": "2026-04-13",
      "score": 4,
      "finalScore": 38.97,
      "direction": "bear",
      "primaryPattern": "头肩顶 H&S Top",
      "patterns": [
        {
          "type": "H&S Top",
          "typeZh": "头肩顶",
          "direction": "bear",
          "status": "Forming",
          "statusZh": "右肩形成中",
          "resistance": null,
          "support": null,
          "ageWeeks": 24
        },
        {
          "type": "Rectangle",
          "typeZh": "矩形整理中",
          "direction": "neutral",
          "status": "区间内 (11次触阻力, 7次触支撑)",
          "statusZh": "区间内 (11次触阻力, 7次触支撑)",
          "resistance": 0.7177,
          "support": 0.6443,
          "ageWeeks": null
        }
      ],
      "trade": {
        "entry": 0.7177,
        "stop": 0.7193,
        "target": 0.6251,
        "riskPct": 0.5,
        "rr": 25.17
      }
    },
    {
      "symbol": "AUDUSD=X",
      "nameEn": "AUD/USD",
      "nameZh": "澳元/美元",
      "category": "forex",
      "lastPrice": 0.7163,
      "lastDate": "2026-04-13",
      "score": 4,
      "finalScore": 38.89,
      "direction": "bear",
      "primaryPattern": "头肩顶 H&S Top",
      "patterns": [
        {
          "type": "H&S Top",
          "typeZh": "头肩顶",
          "direction": "bear",
          "status": "Forming",
          "statusZh": "右肩形成中",
          "resistance": null,
          "support": null,
          "ageWeeks": 24
        },
        {
          "type": "Rectangle",
          "typeZh": "矩形整理中",
          "direction": "neutral",
          "status": "区间内 (11次触阻力, 7次触支撑)",
          "statusZh": "区间内 (11次触阻力, 7次触支撑)",
          "resistance": 0.7175,
          "support": 0.6443,
          "ageWeeks": null
        }
      ],
      "trade": {
        "entry": 0.7175,
        "stop": 0.7197,
        "target": 0.6257,
        "riskPct": 0.47,
        "rr": 26.65
      }
    },
    {
      "symbol": "EURAUD=X",
      "nameEn": "EUR/AUD",
      "nameZh": "欧元/澳元",
      "category": "forex",
      "lastPrice": 1.6439,
      "lastDate": "2026-04-13",
      "score": 2,
      "finalScore": 30.95,
      "direction": "bull",
      "primaryPattern": "矩形整理中 Rectangle Forming",
      "patterns": [
        {
          "type": "Rectangle",
          "typeZh": "矩形整理中",
          "direction": "neutral",
          "status": "区间内 (11次触阻力, 8次触支撑)",
          "statusZh": "区间内 (11次触阻力, 8次触支撑)",
          "resistance": 1.7958,
          "support": 1.6144,
          "ageWeeks": null
        },
        {
          "type": "Falling Wedge",
          "typeZh": "下降楔形",
          "direction": "bull",
          "status": "楔形成立中",
          "statusZh": "楔形成立中",
          "resistance": null,
          "support": null,
          "ageWeeks": null
        }
      ],
      "trade": {
        "entry": 1.7958,
        "stop": 1.6097,
        "target": null,
        "riskPct": 2.08,
        "rr": null
      }
    },
    {
      "symbol": "LBR=F",
      "nameEn": "Lumber",
      "nameZh": "木材",
      "category": "futures",
      "lastPrice": 584.0,
      "lastDate": "2026-04-13",
      "score": 2,
      "finalScore": 30.56,
      "direction": "bear",
      "primaryPattern": "矩形整理中 Rectangle Forming",
      "patterns": [
        {
          "type": "Rectangle",
          "typeZh": "矩形整理中",
          "direction": "neutral",
          "status": "区间内 (6次触阻力, 7次触支撑)",
          "statusZh": "区间内 (6次触阻力, 7次触支撑)",
          "resistance": 618.25,
          "support": 524.25,
          "ageWeeks": null
        },
        {
          "type": "Rising Wedge",
          "typeZh": "上升楔形",
          "direction": "bear",
          "status": "楔形成立中",
          "statusZh": "楔形成立中",
          "resistance": null,
          "support": null,
          "ageWeeks": null
        }
      ],
      "trade": {
        "entry": 618.25,
        "stop": 614.5,
        "target": null,
        "riskPct": 5.22,
        "rr": null
      }
    },
    {
      "symbol": "GF=F",
      "nameEn": "Feeder Cattle",
      "nameZh": "育肥牛",
      "category": "futures",
      "lastPrice": 366.925,
      "lastDate": "2026-04-13",
      "score": 1,
      "finalScore": 29.1,
      "direction": "bear",
      "primaryPattern": "上升楔形 Rising Wedge",
      "patterns": [
        {
          "type": "Rising Wedge",
          "typeZh": "上升楔形",
          "direction": "bear",
          "status": "楔形成立中",
          "statusZh": "楔形成立中",
          "resistance": null,
          "support": null,
          "ageWeeks": null
        }
      ],
      "trade": {
        "entry": null,
        "stop": 378.5,
        "target": null,
        "riskPct": 3.15,
        "rr": null
      }
    },
    {
      "symbol": "CC=F",
      "nameEn": "Cocoa",
      "nameZh": "可可",
      "category": "futures",
      "lastPrice": 3504.0,
      "lastDate": "2026-04-13",
      "score": 1,
      "finalScore": 28.82,
      "direction": "bull",
      "primaryPattern": "下降楔形 Falling Wedge",
      "patterns": [
        {
          "type": "Falling Wedge",
          "typeZh": "下降楔形",
          "direction": "bull",
          "status": "已确认上破",
          "statusZh": "已确认上破",
          "resistance": null,
          "support": null,
          "ageWeeks": null
        }
      ],
      "trade": {
        "entry": null,
        "stop": 2992.0,
        "target": null,
        "riskPct": 14.61,
        "rr": null
      }
    },
    {
      "symbol": "KC=F",
      "nameEn": "Coffee",
      "nameZh": "咖啡",
      "category": "futures",
      "lastPrice": 290.65,
      "lastDate": "2026-04-13",
      "score": 1,
      "finalScore": 28.74,
      "direction": "bull",
      "primaryPattern": "下降楔形 Falling Wedge",
      "patterns": [
        {
          "type": "Falling Wedge",
          "typeZh": "下降楔形",
          "direction": "bull",
          "status": "已确认上破",
          "statusZh": "已确认上破",
          "resistance": null,
          "support": null,
          "ageWeeks": null
        }
      ],
      "trade": {
        "entry": null,
        "stop": 284.3,
        "target": null,
        "riskPct": 2.18,
        "rr": null
      }
    },
    {
      "symbol": "GOOGL",
      "nameEn": "Google",
      "nameZh": "谷歌",
      "category": "stocks_etf",
      "lastPrice": 336.02,
      "lastDate": "2026-04-13",
      "score": 3,
      "finalScore": 27.52,
      "direction": "bear",
      "primaryPattern": "头肩顶 H&S Top",
      "patterns": [
        {
          "type": "H&S Top",
          "typeZh": "头肩顶",
          "direction": "bear",
          "status": "Forming",
          "statusZh": "右肩形成中",
          "resistance": null,
          "support": null,
          "ageWeeks": 4
        }
      ],
      "trade": {
        "entry": null,
        "stop": 339.88,
        "target": 243.0689,
        "riskPct": 1.15,
        "rr": 24.08
      }
    },
    {
      "symbol": "IBIT",
      "nameEn": "ETF IBIT",
      "nameZh": "比特币",
      "category": "stocks_etf",
      "lastPrice": 42.73,
      "lastDate": "2026-04-13",
      "score": 1,
      "finalScore": 27.26,
      "direction": "bull",
      "primaryPattern": "下降楔形 Falling Wedge",
      "patterns": [
        {
          "type": "Falling Wedge",
          "typeZh": "下降楔形",
          "direction": "bull",
          "status": "已确认上破",
          "statusZh": "已确认上破",
          "resistance": null,
          "support": null,
          "ageWeeks": null
        }
      ],
      "trade": {
        "entry": null,
        "stop": 37.13,
        "target": null,
        "riskPct": 13.11,
        "rr": null
      }
    },
    {
      "symbol": "BTC-USD",
      "nameEn": "Bitcoin",
      "nameZh": "比特币",
      "category": "crypto",
      "lastPrice": 74785.8203,
      "lastDate": "2026-04-13",
      "score": 1,
      "finalScore": 26.94,
      "direction": "bull",
      "primaryPattern": "下降楔形 Falling Wedge",
      "patterns": [
        {
          "type": "Falling Wedge",
          "typeZh": "下降楔形",
          "direction": "bull",
          "status": "已确认上破",
          "statusZh": "已确认上破",
          "resistance": null,
          "support": null,
          "ageWeeks": null
        }
      ],
      "trade": {
        "entry": null,
        "stop": 64971.707,
        "target": null,
        "riskPct": 13.12,
        "rr": null
      }
    },
    {
      "symbol": "HG=F",
      "nameEn": "Copper",
      "nameZh": "铜",
      "category": "futures",
      "lastPrice": 6.0435,
      "lastDate": "2026-04-13",
      "score": 1,
      "finalScore": 26.19,
      "direction": "bear",
      "primaryPattern": "上升楔形 Rising Wedge",
      "patterns": [
        {
          "type": "Rising Wedge",
          "typeZh": "上升楔形",
          "direction": "bear",
          "status": "楔形成立中",
          "statusZh": "楔形成立中",
          "resistance": null,
          "support": null,
          "ageWeeks": null
        }
      ],
      "trade": {
        "entry": null,
        "stop": 6.084,
        "target": null,
        "riskPct": 0.67,
        "rr": null
      }
    },
    {
      "symbol": "DOGE-USD",
      "nameEn": "Dogecoin",
      "nameZh": "狗狗币",
      "category": "crypto",
      "lastPrice": 0.0984,
      "lastDate": "2026-04-13",
      "score": 1,
      "finalScore": 25.95,
      "direction": "bull",
      "primaryPattern": "下降楔形 Falling Wedge",
      "patterns": [
        {
          "type": "Falling Wedge",
          "typeZh": "下降楔形",
          "direction": "bull",
          "status": "初步上破，待确认",
          "statusZh": "初步上破，待确认",
          "resistance": null,
          "support": null,
          "ageWeeks": null
        }
      ],
      "trade": {
        "entry": null,
        "stop": 0.0886,
        "target": null,
        "riskPct": 9.98,
        "rr": null
      }
    },
    {
      "symbol": "MSTR",
      "nameEn": "MicroStrategy",
      "nameZh": "微策略",
      "category": "stocks_etf",
      "lastPrice": 148.94,
      "lastDate": "2026-04-13",
      "score": 1,
      "finalScore": 25.42,
      "direction": "bull",
      "primaryPattern": "下降楔形 Falling Wedge",
      "patterns": [
        {
          "type": "Falling Wedge",
          "typeZh": "下降楔形",
          "direction": "bull",
          "status": "初步上破，待确认",
          "statusZh": "初步上破，待确认",
          "resistance": null,
          "support": null,
          "ageWeeks": null
        }
      ],
      "trade": {
        "entry": null,
        "stop": 116.4,
        "target": null,
        "riskPct": 21.85,
        "rr": null
      }
    },
    {
      "symbol": "ETH-USD",
      "nameEn": "Ethereum",
      "nameZh": "以太坊",
      "category": "crypto",
      "lastPrice": 2338.1599,
      "lastDate": "2026-04-13",
      "score": 1,
      "finalScore": 25.39,
      "direction": "bull",
      "primaryPattern": "下降楔形 Falling Wedge",
      "patterns": [
        {
          "type": "Falling Wedge",
          "typeZh": "下降楔形",
          "direction": "bull",
          "status": "已确认上破",
          "statusZh": "已确认上破",
          "resistance": null,
          "support": null,
          "ageWeeks": null
        }
      ],
      "trade": {
        "entry": null,
        "stop": 1939.5287,
        "target": null,
        "riskPct": 17.05,
        "rr": null
      }
    },
    {
      "symbol": "PA=F",
      "nameEn": "Palladium",
      "nameZh": "钯金",
      "category": "futures",
      "lastPrice": 1561.0,
      "lastDate": "2026-04-13",
      "score": 1,
      "finalScore": 25.01,
      "direction": "bull",
      "primaryPattern": "下降楔形 Falling Wedge",
      "patterns": [
        {
          "type": "Falling Wedge",
          "typeZh": "下降楔形",
          "direction": "bull",
          "status": "楔形成立中",
          "statusZh": "楔形成立中",
          "resistance": null,
          "support": null,
          "ageWeeks": null
        }
      ],
      "trade": {
        "entry": null,
        "stop": 1341.3,
        "target": null,
        "riskPct": 14.07,
        "rr": null
      }
    },
    {
      "symbol": "BNB-USD",
      "nameEn": "BNB",
      "nameZh": "币安币",
      "category": "crypto",
      "lastPrice": 631.36,
      "lastDate": "2026-04-13",
      "score": 1,
      "finalScore": 24.52,
      "direction": "bull",
      "primaryPattern": "下降楔形 Falling Wedge",
      "patterns": [
        {
          "type": "Falling Wedge",
          "typeZh": "下降楔形",
          "direction": "bull",
          "status": "初步上破，待确认",
          "statusZh": "初步上破，待确认",
          "resistance": null,
          "support": null,
          "ageWeeks": null
        }
      ],
      "trade": {
        "entry": null,
        "stop": 570.684,
        "target": null,
        "riskPct": 9.61,
        "rr": null
      }
    },
    {
      "symbol": "XRP-USD",
      "nameEn": "XRP",
      "nameZh": "瑞波",
      "category": "crypto",
      "lastPrice": 1.4309,
      "lastDate": "2026-04-13",
      "score": 1,
      "finalScore": 24.3,
      "direction": "bull",
      "primaryPattern": "下降楔形 Falling Wedge",
      "patterns": [
        {
          "type": "Falling Wedge",
          "typeZh": "下降楔形",
          "direction": "bull",
          "status": "初步上破，待确认",
          "statusZh": "初步上破，待确认",
          "resistance": null,
          "support": null,
          "ageWeeks": null
        }
      ],
      "trade": {
        "entry": null,
        "stop": 1.281,
        "target": null,
        "riskPct": 10.48,
        "rr": null
      }
    },
    {
      "symbol": "SOL-USD",
      "nameEn": "Solana",
      "nameZh": "索拉纳",
      "category": "crypto",
      "lastPrice": 88.26,
      "lastDate": "2026-04-13",
      "score": 1,
      "finalScore": 22.27,
      "direction": "bull",
      "primaryPattern": "下降楔形 Falling Wedge",
      "patterns": [
        {
          "type": "Falling Wedge",
          "typeZh": "下降楔形",
          "direction": "bull",
          "status": "初步上破，待确认",
          "statusZh": "初步上破，待确认",
          "resistance": null,
          "support": null,
          "ageWeeks": null
        }
      ],
      "trade": {
        "entry": null,
        "stop": 76.8169,
        "target": null,
        "riskPct": 12.97,
        "rr": null
      }
    },
    {
      "symbol": "ADA-USD",
      "nameEn": "Cardano",
      "nameZh": "艾达",
      "category": "crypto",
      "lastPrice": 0.2563,
      "lastDate": "2026-04-13",
      "score": 1,
      "finalScore": 21.46,
      "direction": "bull",
      "primaryPattern": "下降楔形 Falling Wedge",
      "patterns": [
        {
          "type": "Falling Wedge",
          "typeZh": "下降楔形",
          "direction": "bull",
          "status": "初步上破，待确认",
          "statusZh": "初步上破，待确认",
          "resistance": null,
          "support": null,
          "ageWeeks": null
        }
      ],
      "trade": {
        "entry": null,
        "stop": 0.2347,
        "target": null,
        "riskPct": 8.43,
        "rr": null
      }
    },
    {
      "symbol": "NG=F",
      "nameEn": "Natural Gas",
      "nameZh": "天然气",
      "category": "futures",
      "lastPrice": 2.662,
      "lastDate": "2026-04-13",
      "score": 1,
      "finalScore": 14.6,
      "direction": "bull",
      "primaryPattern": "下降楔形 Falling Wedge",
      "patterns": [
        {
          "type": "Falling Wedge",
          "typeZh": "下降楔形",
          "direction": "bull",
          "status": "楔形成立中",
          "statusZh": "楔形成立中",
          "resistance": null,
          "support": null,
          "ageWeeks": null
        }
      ],
      "trade": {
        "entry": null,
        "stop": 2.561,
        "target": null,
        "riskPct": 3.79,
        "rr": null
      }
    },
    {
      "symbol": "ZR=F",
      "nameEn": "Rough Rice",
      "nameZh": "糙米",
      "category": "futures",
      "lastPrice": 11.205,
      "lastDate": "2026-04-13",
      "score": 5,
      "finalScore": 13.74,
      "direction": "bear",
      "primaryPattern": "扩展三角形 Horn / Expanding Triangle",
      "patterns": [
        {
          "type": "扩展三角形 Horn / Expanding Triangle",
          "typeZh": "扩展三角形 Horn / Expanding Triangle",
          "direction": "neutral",
          "status": "波动放大中",
          "statusZh": "波动放大中",
          "resistance": null,
          "support": null,
          "ageWeeks": null
        },
        {
          "type": "Wide Bodied Bar",
          "typeZh": "宽体K线",
          "direction": "bear",
          "status": "本周WBB (看跌), 范围是均值的23.1倍",
          "statusZh": "本周WBB (看跌), 范围是均值的23.1倍",
          "resistance": null,
          "support": null,
          "ageWeeks": null
        }
      ],
      "trade": {
        "entry": null,
        "stop": 316.572,
        "target": null,
        "riskPct": 2725.27,
        "rr": null
      }
    }
  ]
}